odoo/addons/contract_layout_category_hide_detail/README.rst
odoo/addons/contract_layout_category_hide_detail/__init__.py
odoo/addons/contract_layout_category_hide_detail/__manifest__.py
odoo/addons/contract_layout_category_hide_detail/i18n/contract_layout_category_hide_detail.pot
odoo/addons/contract_layout_category_hide_detail/i18n/pt_BR.po
odoo/addons/contract_layout_category_hide_detail/models/__init__.py
odoo/addons/contract_layout_category_hide_detail/models/abstract_contract_line.py
odoo/addons/contract_layout_category_hide_detail/models/contract_line.py
odoo/addons/contract_layout_category_hide_detail/readme/CONTRIBUTORS.rst
odoo/addons/contract_layout_category_hide_detail/readme/DESCRIPTION.rst
odoo/addons/contract_layout_category_hide_detail/readme/ROADMAP.rst
odoo/addons/contract_layout_category_hide_detail/readme/USAGE.rst
odoo/addons/contract_layout_category_hide_detail/static/description/icon.png
odoo/addons/contract_layout_category_hide_detail/static/description/index.html
odoo/addons/contract_layout_category_hide_detail/static/description/readme-icons/eye-slash.png
odoo/addons/contract_layout_category_hide_detail/static/description/readme-icons/eye.png
odoo/addons/contract_layout_category_hide_detail/static/description/readme-icons/minus-circle.png
odoo/addons/contract_layout_category_hide_detail/static/description/readme-icons/plus-circle.png
odoo/addons/contract_layout_category_hide_detail/views/abstract_contract_line.xml
odoo/addons/contract_layout_category_hide_detail/views/contract.xml
odoo12_addon_contract_layout_category_hide_detail-12.0.1.0.0.99.dev7.dist-info/METADATA
odoo12_addon_contract_layout_category_hide_detail-12.0.1.0.0.99.dev7.dist-info/WHEEL
odoo12_addon_contract_layout_category_hide_detail-12.0.1.0.0.99.dev7.dist-info/top_level.txt
odoo12_addon_contract_layout_category_hide_detail-12.0.1.0.0.99.dev7.dist-info/RECORD
